lmmaes/__init__.py
lmmaes/lmmaes.py
lmmaes-0.3.2.dist-info/LICENSE
lmmaes-0.3.2.dist-info/METADATA
lmmaes-0.3.2.dist-info/WHEEL
lmmaes-0.3.2.dist-info/top_level.txt
lmmaes-0.3.2.dist-info/RECORD
