Metadata-Version: 2.1
Name: lmmaes
Version: 0.3.2
Summary: Limited-Memory Matrix Adaptation Evolution Strategy
Home-page: https://github.com/giuse/lmmaes
Author: Giuseppe Cuccu
Author-email: giuseppe.cuccu@gmail.com
Keywords: black-box optimization,evolution strategies,large scale
Requires-Python: >=3.6
License-File: LICENSE
Requires-Dist: numpy
